ncc_cursofiap/__init__.py
ncc_cursofiap/core.py
ncc_cursofiap_package-1.0.0.dist-info/METADATA
ncc_cursofiap_package-1.0.0.dist-info/WHEEL
ncc_cursofiap_package-1.0.0.dist-info/top_level.txt
ncc_cursofiap_package-1.0.0.dist-info/RECORD
