Metadata-Version: 2.1
Name: ncc-cursofiap-package
Version: 1.0.0
Summary: Descricao da sua lib ncc_cursofiap
Home-page: https://github.com/tadrianonet/ncc_cursofiap
Author: Robson Nicácio
Author-email: robson.nicacio@gmail.com
License: MIT
